python_sdk_rafay_workflow/__init__.py
python_sdk_rafay_workflow/activity_logger.py
python_sdk_rafay_workflow/const.py
python_sdk_rafay_workflow/errors.py
python_sdk_rafay_workflow/sdk.py
python_sdk_rafay_workflow-0.0.22.dist-info/METADATA
python_sdk_rafay_workflow-0.0.22.dist-info/WHEEL
python_sdk_rafay_workflow-0.0.22.dist-info/licenses/LICENSE
python_sdk_rafay_workflow-0.0.22.dist-info/RECORD
