Metadata-Version: 2.3
Name: python_sdk_rafay_workflow
Version: 0.0.22
Summary: Rafay workflow handler Python function SDK
Project-URL: Homepage, https://github.com/RafaySystems/function-templates
Project-URL: Issues, https://github.com/RafaySystems/function-templates/issues
Author-email: Bheema Sarat Chandra Kaki <sarat@rafay.co>
License-File: LICENSE
Classifier: License :: OSI Approved :: MIT License
Classifier: Operating System :: OS Independent
Classifier: Programming Language :: Python :: 3
Requires-Python: >=3.11
Requires-Dist: flask>=3.0.2
Requires-Dist: requests-toolbelt>=1.0.0
Requires-Dist: requests>=2.31.0
Requires-Dist: waitress>=3.0.0
